chopsticksc/__init__.py
chopsticksc/strategy.csv
chopsticksc-1.0.5.dist-info/DESCRIPTION.rst
chopsticksc-1.0.5.dist-info/METADATA
chopsticksc-1.0.5.dist-info/RECORD
chopsticksc-1.0.5.dist-info/WHEEL
chopsticksc-1.0.5.dist-info/metadata.json
chopsticksc-1.0.5.dist-info/top_level.txt
