Metadata-Version: 2.0
Name: chopsticksc
Version: 1.0.5
Summary: This module allows a human to play chopsticks against either another human or a computer.
Requires-Dist: pandas
